deepcut/__init__.py
deepcut/deepcut.py
deepcut/model.py
deepcut/stop_words.py
deepcut/train.py
deepcut/utils.py
deepcut/weight/cnn_without_ne_ab.h5
deepcut-0.7.0.0.dist-info/LICENSE
deepcut-0.7.0.0.dist-info/METADATA
deepcut-0.7.0.0.dist-info/WHEEL
deepcut-0.7.0.0.dist-info/top_level.txt
deepcut-0.7.0.0.dist-info/RECORD
