Metadata-Version: 2.1
Name: deepcut
Version: 0.7.0.0
Summary: A Thai word tokenization library using Deep Neural Network
Home-page: https://github.com/rkcosmos/deepcut
Author: Rakpong Kittinaradorn
Author-email: r.kittinaradorn@gmail.com
License: MIT
Download-URL: https://github.com/rkcosmos/deepcut.git
Keywords: thai word segmentation deep learning neural network development
Platform: UNKNOWN
Classifier: Development Status :: 3 - Alpha
Requires-Dist: tensorflow (>=2.0.0)
Requires-Dist: pandas
Requires-Dist: scipy
Requires-Dist: numpy
Requires-Dist: scikit-learn
Requires-Dist: h5py
